versioning_fs
