Metadata-Version: 1.0
Name: versioning-fs
Version: 0.1.2
Summary: Incremental versioning file system for PyFileSystem
Home-page: http://github.com/travcunn/file-versioning
Author: Travis Cunningham
Author-email: travcunn@umail.iu.edu
License: MIT
Platform: UNKNOWN
